previewer/__init__.py
previewer/cli.py
previewer/collectors.py
previewer/filters.py
previewer/font.py
previewer/mime.py
previewer/montage.py
previewer/resolution.py
previewer/resources/Fira_Sans/FiraSans-Black.ttf
previewer/resources/Fira_Sans/FiraSans-BlackItalic.ttf
previewer/resources/Fira_Sans/FiraSans-Bold.ttf
previewer/resources/Fira_Sans/FiraSans-BoldItalic.ttf
previewer/resources/Fira_Sans/FiraSans-ExtraBold.ttf
previewer/resources/Fira_Sans/FiraSans-ExtraBoldItalic.ttf
previewer/resources/Fira_Sans/FiraSans-ExtraLight.ttf
previewer/resources/Fira_Sans/FiraSans-ExtraLightItalic.ttf
previewer/resources/Fira_Sans/FiraSans-Italic.ttf
previewer/resources/Fira_Sans/FiraSans-Light.ttf
previewer/resources/Fira_Sans/FiraSans-LightItalic.ttf
previewer/resources/Fira_Sans/FiraSans-Medium.ttf
previewer/resources/Fira_Sans/FiraSans-MediumItalic.ttf
previewer/resources/Fira_Sans/FiraSans-Regular.ttf
previewer/resources/Fira_Sans/FiraSans-SemiBold.ttf
previewer/resources/Fira_Sans/FiraSans-SemiBoldItalic.ttf
previewer/resources/Fira_Sans/FiraSans-Thin.ttf
previewer/resources/Fira_Sans/FiraSans-ThinItalic.ttf
previewer/resources/Fira_Sans/OFL.txt
previewer/resources/__init__.py
previewer/utils.py
previewer/video.py
previewer-0.9.0.dist-info/LICENSE
previewer-0.9.0.dist-info/METADATA
previewer-0.9.0.dist-info/WHEEL
previewer-0.9.0.dist-info/entry_points.txt
previewer-0.9.0.dist-info/RECORD
