Metadata-Version: 2.1
Name: previewer
Version: 0.9.0
Summary: Video or Folder preview generator
Home-page: https://github.com/essembeh/previewer
License: Apache-2.0
Author: Sébastien MB
Author-email: seb@essembeh.org
Requires-Python: >=3.10,<4.0
Classifier: Development Status :: 4 - Beta
Classifier: License :: OSI Approved :: Apache Software License
Classifier: Programming Language :: Python :: 3
Classifier: Programming Language :: Python :: 3.10
Classifier: Programming Language :: Python :: 3.11
Classifier: Topic :: Utilities
Requires-Dist: colorama (>=0.4.6,<0.5.0)
Requires-Dist: pillow (>=10.0.0,<11.0.0)
Requires-Dist: puremagic (>=1.15,<2.0)
